setup.py
tree_output/__init__.py
tree_output/houtput.py
tree_output/log_handler.py
tree_output.egg-info/PKG-INFO
tree_output.egg-info/SOURCES.txt
tree_output.egg-info/dependency_links.txt
tree_output.egg-info/pbr.json
tree_output.egg-info/requires.txt
tree_output.egg-info/top_level.txt